azure/mgmt/web/__init__.py
azure/mgmt/web/_configuration.py
azure/mgmt/web/_operations_mixin.py
azure/mgmt/web/_serialization.py
azure/mgmt/web/_version.py
azure/mgmt/web/_web_site_management_client.py
azure/mgmt/web/models.py
azure/mgmt/web/py.typed
azure/mgmt/web/aio/__init__.py
azure/mgmt/web/aio/_configuration.py
azure/mgmt/web/aio/_operations_mixin.py
azure/mgmt/web/aio/_web_site_management_client.py
azure/mgmt/web/v2016_03_01/__init__.py
azure/mgmt/web/v2016_03_01/_configuration.py
azure/mgmt/web/v2016_03_01/_patch.py
azure/mgmt/web/v2016_03_01/_vendor.py
azure/mgmt/web/v2016_03_01/_version.py
azure/mgmt/web/v2016_03_01/_web_site_management_client.py
azure/mgmt/web/v2016_03_01/py.typed
azure/mgmt/web/v2016_03_01/aio/__init__.py
azure/mgmt/web/v2016_03_01/aio/_configuration.py
azure/mgmt/web/v2016_03_01/aio/_patch.py
azure/mgmt/web/v2016_03_01/aio/_vendor.py
azure/mgmt/web/v2016_03_01/aio/_web_site_management_client.py
azure/mgmt/web/v2016_03_01/aio/operations/__init__.py
azure/mgmt/web/v2016_03_01/aio/operations/_billing_meters_operations.py
azure/mgmt/web/v2016_03_01/aio/operations/_certificates_operations.py
azure/mgmt/web/v2016_03_01/aio/operations/_deleted_web_apps_operations.py
azure/mgmt/web/v2016_03_01/aio/operations/_diagnostics_operations.py
azure/mgmt/web/v2016_03_01/aio/operations/_patch.py
azure/mgmt/web/v2016_03_01/aio/operations/_provider_operations.py
azure/mgmt/web/v2016_03_01/aio/operations/_recommendations_operations.py
azure/mgmt/web/v2016_03_01/aio/operations/_resource_health_metadata_operations.py
azure/mgmt/web/v2016_03_01/aio/operations/_web_site_management_client_operations.py
azure/mgmt/web/v2016_03_01/models/__init__.py
azure/mgmt/web/v2016_03_01/models/_models_py3.py
azure/mgmt/web/v2016_03_01/models/_patch.py
azure/mgmt/web/v2016_03_01/models/_web_site_management_client_enums.py
azure/mgmt/web/v2016_03_01/operations/__init__.py
azure/mgmt/web/v2016_03_01/operations/_billing_meters_operations.py
azure_mgmt_web-8.0.0.dist-info/LICENSE
azure_mgmt_web-8.0.0.dist-info/METADATA
azure_mgmt_web-8.0.0.dist-info/WHEEL
azure_mgmt_web-8.0.0.dist-info/top_level.txt
azure_mgmt_web-8.0.0.dist-info/RECORD
